czech_syllable_splitter/__init__.py
czech_syllable_splitter/czech_syllable_splitter.py
czech_syllable_splitter-0.1.0.dist-info/LICENSE
czech_syllable_splitter-0.1.0.dist-info/METADATA
czech_syllable_splitter-0.1.0.dist-info/WHEEL
czech_syllable_splitter-0.1.0.dist-info/RECORD
