Metadata-Version: 2.1
Name: czech-syllable-splitter
Version: 0.1.0
Summary: Splitting Czech words into syllables
Home-page: https://github.com/adasek/czech-syllable-splitter
License: MIT
Keywords: syllables,syllable,czech,czech-language,language,count,counter,natural-language-processing,nlp
Author: Adam Benda
Author-email: adam@adasek.cz
Requires-Python: >=3.8,<4.0
Classifier: Development Status :: 4 - Beta
Classifier: License :: OSI Approved :: MIT License
Classifier: Programming Language :: Python :: 3
Classifier: Programming Language :: Python :: 3.8
Classifier: Programming Language :: Python :: 3.9
Classifier: Programming Language :: Python :: 3.10
Classifier: Programming Language :: Python :: 3.11
Classifier: Programming Language :: Python :: 3.12
Project-URL: Repository, https://github.com/adasek/czech-syllable-splitter
